Workbook

Sheet LT cost
A1: 2018-19 Rates | H1: 2019-20 Rates | O1: 2020/21 Rates | W1: 2021/22 Rates | AE1: 2022/23 Rates | AM1: 2023/24 Rates | AU1: 2024/25 Rates
A2: need level | B2: Matrix rate for shared lives week | C2: matrix rate for alternative service per session | D2: standard holiday weeks | H2: need level | I2: Matrix rate for shared lives week | J2: matrix rate for alternative service per session | K2: standard holiday weeks | O2: need level | P2: Matrix rate for shared lives week | Q2: matrix rate for alternative day service per session | R2: standard holiday weeks | W2: need level | X2: Matrix rate for shared lives week | Y2: matrix rate for alternative day service per session | Z2: standard holiday weeks | AE2: need level | AF2: Matrix rate for shared lives week | AG2: matrix rate for alternative day service per session | AH2: standard holiday weeks | AM2: need level | AN2: Matrix rate for shared lives week | AO2: matrix rate for alternative day service per session | AP2: standard holiday weeks | AU2: need level | AV2: Matrix rate for shared lives week | AW2: matrix rate for alternative day service per session | AX2: standard holiday weeks
A3: Basic | B3: 210.68 | C3: 0 | D3: n/a | H3: Basic | I3: =+B3+15 -> 225.68 | J3: 0 | K3: n/a | M3: =+I3/B3 -> 1.071198 | O3: Basic | P3: 236.2 | Q3: 0 | R3: n/a | W3: Basic | X3: =ROUND(P3*1.0156,2) -> 239.88 | Y3: 0 | Z3: n/a | AA3: payment | AB3: increase by 1.56% | AE3: Basic | AF3: =ROUND(X3*1.0558,2) -> 253.27 | AG3: 0 | AH3: n/a | AI3: payment | AJ3: increase by 5.58% | AM3: Basic | AN3: =ROUND(AF3*1.0687,2) -> 270.67 | AO3: 0 | AP3: n/a | AR3: increase by 6.87% | AU3: Basic | AV3: =ROUND(AN3*1.07,2) -> 289.62 | AW3: 0 | AX3: n/a | AZ3: increase by 7%
A4: Low | B4: 322.86 | C4: 7.74 | D4: 4 | E4: what increase on day service? | H4: Low | I4: =+B4+15 -> 337.86 | J4: =+C4*M4 -> 8.0995986 | K4: 4 | M4: =+I4/B4 -> 1.0464598 | O4: Low | P4: 353.6 | Q4: 9.47 | R4: 4 | W4: Low | X4: =ROUND(P4*1.0156,2) -> 359.12 | Y4: =ROUND(Q4*1.0165,2) -> 9.63 | Z4: 4 | AE4: Low | AF4: =ROUND(X4*1.0558,2) -> 379.16 | AG4: =ROUND(Y4*1.0585,2) -> 10.19 | AH4: 4 | AM4: Low | AN4: =ROUND(AF4*1.0687,2) -> 405.21 | AO4: 10.95 | AP4: 4 | AU4: Low | AV4: =ROUND(AN4*1.07,2) -> 433.57 | AW4: 11.79 | AX4: 4
A5: Medium | B5: 455.29 | C5: 11.36 | D5: 4 | H5: Medium | I5: =+B5+15 -> 470.29 | J5: =+C5*M5 -> 11.734267 | K5: 4 | M5: =+I5/B5 -> 1.032946 | O5: Medium | P5: 492.21 | Q5: 13.74 | R5: 4 | W5: Medium | X5: =ROUND(P5*1.0156,2) -> 499.89 | Y5: =ROUND(Q5*1.0165,2) -> 13.97 | Z5: 4 | AE5: Medium | AF5: =ROUND(X5*1.0558,2) -> 527.78 | AG5: =ROUND(Y5*1.0585,2) -> 14.79 | AH5: 4 | AM5: Medium | AN5: =ROUND(AF5*1.0687,2) -> 564.04 | AO5: 15.89 | AP5: 4 | AU5: Medium | AV5: =ROUND(AN5*1.07,2)+3 -> 606.52 | AW5: 17.11 | AX5: 4
A6: High | B6: 600.85 | C6: 17.04 | D6: 4 | H6: High | I6: =+B6+15 -> 615.85 | J6: =+C6*M6 -> 17.465397 | K6: 4 | M6: =+I6/B6 -> 1.0249646 | O6: High | P6: 644.55 | Q6: 19.41 | R6: 4 | W6: High | X6: =ROUND(P6*1.0156,2) -> 654.6 | Y6: =ROUND(Q6*1.0165,2) -> 19.73 | Z6: 4 | AE6: High | AF6: =ROUND(X6*1.0558,2) -> 691.13 | AG6: =ROUND(Y6*1.0585,2) -> 20.88 | AH6: 4 | AM6: High | AN6: =ROUND(AF6*1.0687,2) -> 738.61 | AO6: 22.44 | AP6: 4 | AU6: High | AV6: =ROUND(AN6*1.07,2) -> 790.31 | AW6: 24.16 | AX6: 4
A7: Complex | B7: 866.8 | C7: 33.04 | D7: 6 | H7: Complex | I7: =+B7+15 -> 881.8 | J7: =+C7*M7 -> 33.611758 | K7: 6 | M7: =+I7/B7 -> 1.017305 | O7: Complex | P7: 922.89 | Q7: 37.63 | R7: 6 | W7: Complex | X7: =ROUND(P7*1.0156,2) -> 937.29 | Y7: =ROUND(Q7*1.0165,2) -> 38.25 | Z7: 6 | AE7: Complex | AF7: =ROUND(X7*1.0558,2) -> 989.59 | AG7: =ROUND(Y7*1.0585,2) -> 40.49 | AH7: 6 | AM7: Complex | AN7: =ROUND(AF7*1.0687,2) -> 1057.57 | AO7: 43.5 | AP7: 6 | AU7: Complex | AV7: =ROUND(AN7*1.07,2) -> 1131.6 | AW7: 46.84 | AX7: 6
A9: Name | H9: Name | O9: Name | W9: Name | AE9: Name | AM9: Name | AU9: Name
A10: Matrix score | B10: =P10 -> Complex | H10: Matrix score | I10: =P10 -> Complex | O10: Matrix score | P10: Complex | W10: Matrix score | X10: Medium | AE10: Matrix score | AF10: Medium | AM10: Matrix score | AN10: Medium | AU10: Matrix score
A12: Matrix rate | F12: =VLOOKUP(B10,$A$3:$B$7,2,FALSE) -> 866.8 | H12: Matrix rate | M12: =VLOOKUP(I10,$H$3:$I$7,2,FALSE) -> 881.8 | O12: Matrix rate | T12: =VLOOKUP(P10,$O$3:$Q$7,2,FALSE) -> 922.89 | W12: Matrix rate | AB12: =VLOOKUP(X10,$W$3:$Y$7,2,FALSE) -> 499.89 | AE12: Matrix rate | AJ12: =VLOOKUP(AF10,$AE$3:$AG$7,2,FALSE) -> 527.78 | AM12: Matrix rate | AR12: =VLOOKUP(AN10,$AM$3:$AO$7,2,FALSE) -> 564.04 | AU12: Matrix rate | AZ12: =VLOOKUP(AV10,$AU$3:$AW$7,2,FALSE) -> #N/A
A13: LESS | C13: no. of sessions/wk | D13: amount per session/wk | H13: LESS | J13: no. of sessions/wk | K13: amount per session/wk | O13: LESS | Q13: no. of sessions/wk | R13: amount per session/wk | W13: LESS | Y13: no. of sessions/wk | Z13: amount per session/wk | AE13: LESS | AG13: no. of sessions/wk | AH13: amount per session/wk | AM13: LESS | AO13: no. of sessions/wk | AP13: amount per session/wk | AU13: LESS | AW13: no. of sessions/wk | AX13: amount per session/wk
A14: Alternative sessions | C14: =J14 -> 0 | D14: =+VLOOKUP(B10,$A$3:$C$7,3,FALSE) -> 33.04 | E14: =C14*D14 -> 0 | H14: Alternative sessions | K14: =VLOOKUP(I10,$H$3:$J$7,3,FALSE) -> 33.611758 | L14: =J14*K14 -> 0 | O14: Alternative sessions | Q14: 10 | R14: =VLOOKUP(P10,$O$3:$Q$7,3,FALSE) -> 37.63 | S14: =Q14*R14 -> 376.3 | W14: Alternative sessions | Y14: 10 | Z14: =VLOOKUP(X10,$W$3:$Y$7,3,FALSE) -> 13.97 | AA14: =Y14*Z14 -> 139.7 | AE14: Alternative sessions | AG14: 10 | AH14: =VLOOKUP(AF10,$AE$3:$AG$7,3,FALSE) -> 14.79 | AI14: =AG14*AH14 -> 147.9 | AM14: Alternative sessions | AO14: 10 | AP14: =VLOOKUP(AN10,$AM$3:$AO$7,3,FALSE) -> 15.89 | AQ14: =AO14*AP14 -> 158.9 | AU14: Alternative sessions | AY14: =AW14*AX14 -> 0
A15: additional holiday weeks (matrix score less SU contribution) | C15: =+J15 -> 0 | D15: =F12-(F19+E14+F20) -> 810.8 | E15: =(C15*D15)/52 -> 0 | H15: additional holiday weeks (matrix score less SU contribution) | J15: 0 | K15: =M12-(M19+L14+M20) -> 818.8 | L15: =(J15*K15)/52 -> 0 | O15: additional holiday weeks (matrix score less SU contribution) | Q15: 0 | R15: =T12-(T19+S14+T20) -> 482.54 | S15: =(Q15*R15)/52 -> 0 | W15: additional holiday weeks (matrix score less SU contribution) | Y15: 0 | Z15: =AB12-(AB19+AA14+AB20) -> 295.79 | AA15: =(Y15*Z15)/52 -> 0 | AE15: additional holiday weeks (matrix score less SU contribution) | AG15: 0 | AH15: =AJ12-(AJ19+AI14+AJ20) -> 313.38 | AI15: =(AG15*AH15)/52 -> 0 | AM15: additional holiday weeks (matrix score less SU contribution) | AO15: 0 | AP15: =AR12-(AR19+AQ14+AR20) -> 331.64 | AQ15: =(AO15*AP15)/52 -> 0 | AU15: additional holiday weeks (matrix score less SU contribution) | AW15: 0 | AX15: =AZ12-(AZ19+AY14+AZ20) -> #N/A | AY15: =(AW15*AX15)/52 -> #N/A
E16: =E14+E15 -> 0 | L16: =L14+L15 -> 0 | S16: =S14+S15 -> 376.3 | AA16: =AA14+AA15 -> 139.7 | AI16: =AI14+AI15 -> 147.9 | AQ16: =AQ14+AQ15 -> 158.9 | AY16: =AY14+AY15 -> #N/A
A17: TOTAL CARER INCOME | F17: =F12-E16 -> 866.8 | H17: TOTAL CARER INCOME | M17: =M12-L16 -> 881.8 | O17: TOTAL CARER INCOME | T17: =T12-S16 -> 546.59 | W17: TOTAL CARER INCOME | AB17: =AB12-AA16 -> 360.19 | AE17: TOTAL CARER INCOME | AJ17: =AJ12-AI16 -> 379.88 | AM17: TOTAL CARER INCOME | AR17: =AR12-AQ16 -> 405.14 | AU17: TOTAL CARER INCOME | AZ17: =AZ12-AY16 -> #N/A
A18: Made up of: | H18: Made up of: | O18: Made up of: | W18: Made up of: | AE18: Made up of: | AM18: Made up of: | AU18: Made up of:
A19: Service user contribution | F19: =8*7 -> 56 | H19: Service user contribution | M19: =9*7 -> 63 | O19: Service user contribution | T19: 64.05 | W19: Service user contribution | AB19: 64.4 | AC19: increase in customer contribution by 0.5% | AE19: Service user contribution | AJ19: =9.5*7 -> 66.5 | AM19: Service user contribution | AR19: =10.5*7 -> 73.5 | AU19: Service user contribution | AZ19: 78.4
AU20: housing benefit/Rent | AZ20: 70
A21: Notts CC payment | F21: =F17-(F19+F20) -> 810.8 | H21: Notts CC payment | M21: =M17-(M19+M20) -> 818.8 | O21: Notts CC payment | T21: =T17-(T19+T20) -> 482.54 | W21: Notts CC payment | AB21: =AB17-(AB19+AB20) -> 295.79 | AE21: Notts CC payment | AJ21: =AJ17-(AJ19+AJ20) -> 313.38 | AM21: Notts CC payment | AR21: =AR17-(AR19+AR20) -> 331.64 | AU21: Notts CC payment | AZ21: =AZ17-(AZ19+AZ20) -> #N/A
F22: =F19+F20+F21 -> 866.8 | M22: =M19+M20+M21 -> 881.8 | T22: =T19+T20+T21 -> 546.59 | AB22: =AB19+AB20+AB21 -> 360.19 | AJ22: =AJ19+AJ20+AJ21 -> 379.88 | AR22: =AR19+AR20+AR21 -> 405.14
H24: Total Change since April 2018 | M24: =+M17-$F17 -> 15
H25: NCC Change since April 2018 | M25: =+M21-$F21 -> 8 | AE25: Benefit and pensions rates 2023 to 2024 (publishing.service.gov.uk)
AE27: Universal Credit | AF27: 22/23 | AG27: 23/24
AE28: Standard Allowance
AE29: Single under 25 | AF29: 265.31 | AG29: 292.11 | AH29: =(AG29-AF29)/AF29 -> 0.10101391
AE30: Single 25 or over | AF30: 334.91 | AG30: 368.74 | AH30: =(AG30-AF30)/AF30 -> 0.10101221
AE32: Contribution | AF32: 9.5 | AG32: =+AF32*(1+AH30) -> 10.459616

Sheet ST cost
A1: Short term carer payments | G1: Short term carer payments | M1: Short term carer payments | S1: Short term carer payments | Z1: Short term carer payments | AG1: Short term carer payments | AN1: Short term carer payments
A2: 2018/19 Rates | G2: 2019/20 Rates | M2: 2020/2021 rates | S2: 2021/2022 rates | Z2: 2022/2023 rates | AG2: 2023/2024 rates | AN2: 2024/2025 rates
A3: need level | B3: Matrix rate for shared lives 24 hrs | C3: JUST night rate | D3: JUST day rate | E3: SU contribution per night | G3: need level | H3: Matrix rate for shared lives 24 hrs | I3: JUST night rate | J3: JUST day rate | K3: SU contribution per night | M3: need level | N3: Matrix rate for shared lives 24 hrs | O3: JUST night rate | P3: JUST day rate | Q3: SU contribution per night | S3: need level | T3: Matrix rate for shared lives 24 hrs | U3: JUST night rate | V3: JUST day rate | W3: SU contribution per night | Z3: need level | AA3: Matrix rate for shared lives 24 hrs | AB3: JUST night rate | AC3: JUST day rate | AD3: SU contribution per night | AG3: need level | AH3: Matrix rate for shared lives 24 hrs | AI3: JUST night rate | AJ3: JUST day rate | AK3: SU contribution per night | AN3: need level | AO3: Matrix rate for shared lives 24 hrs | AP3: JUST night rate | AQ3: JUST day rate | AR3: SU contribution per night
A4: Low | B4: 46.12 | C4: 29.71 | D4: 16.42 | E4: 8 | G4: Low | H4: =+B4+$I$24 -> 48.262857 | I4: =ROUND(+$H4*C21,2) -> 31.09 | J4: =ROUND(+$H4*D21,2) -> 17.18 | K4: 9 | M4: Low | N4: =+'LT cost'!P4/7 -> 50.514286 | O4: =+$N4*C21 -> 32.540751 | P4: =+$N4*D21 -> 17.984488 | Q4: 9.15 | S4: Low | T4: =('LT cost'!X4/7) -> 51.302857 | U4: =+$T4*C21 -> 33.04874 | V4: =+$T4*D21 -> 18.265241 | W4: 9.2 | X4: increase of payments by 1.56% | Z4: Low | AA4: =('LT cost'!AF4/7) -> 54.165714 | AB4: =+$AA4*C21 -> 34.892961 | AC4: =+$AA4*D21 -> 19.284498 | AD4: 9.5 | AE4: increase of payments by 5.58% | AG4: Low | AH4: =('LT cost'!AN4/7) -> 57.887143 | AI4: =+$AH4*AB21 -> 37.290265 | AJ4: =+$AH4*AC21 -> 20.609429 | AK4: 10.5 | AL4: increase of payments by 6.87% | AN4: Low | AO4: =ROUND('LT cost'!AV4/7,2) -> 61.94 | AP4: =+$AO4*AI21 -> 39.901748 | AQ4: =+$AO4*AJ21 -> 22.038252 | AR4: 11.2 | AS4: increase of payments by 7%
A5: Medium | B5: 65.04 | C5: 40.97 | D5: 24.08 | E5: 8 | G5: Medium | H5: =+B5+$I$24 -> 67.182857 | I5: =ROUND(+$H5*C22,2) -> 42.32 | J5: =ROUND(+$H5*D22,2) -> 24.87 | K5: 9 | M5: Medium | N5: =+'LT cost'!P5/7 -> 70.315714 | O5: =+$N5*C22 -> 44.293278 | P5: =+$N5*D22 -> 26.033247 | Q5: 9.15 | S5: Medium | T5: =('LT cost'!X5/7) -> 71.412857 | U5: =+$T5*C22 -> 44.98439 | V5: =+$T5*D22 -> 26.439446 | W5: 9.2 | X5: increase in customer contribution by 0.5% | Z5: Medium | AA5: =('LT cost'!AF5/7) -> 75.397143 | AB5: =+$AA5*C22 -> 47.494172 | AC5: =+$AA5*D22 -> 27.914563 | AD5: 9.5 | AE5: increase in customer contribution by 3.1% | AG5: Medium | AH5: =('LT cost'!AN5/7) -> 80.577143 | AI5: =+$AH5*AB22 -> 50.757158 | AJ5: =+$AH5*AC22 -> 29.832374 | AK5: 10.5 | AL5: increase in customer contribution by 10.1% | AN5: Medium | AO5: =ROUND('LT cost'!AV5/7,2) -> 86.65 | AP5: =+$AO5*AI22 -> 54.580835 | AQ5: =+$AO5*AJ22 -> 32.069165 | AR5: 11.2 | AS5: increase in customer contribution by 6.7%
A6: High | B6: 85.83 | C6: 49.73 | D6: 36.12 | E6: 8 | G6: High | H6: =+B6+$I$24 -> 87.972857 | I6: =ROUND(+$H6*C23,2) -> 50.97 | J6: =ROUND(+$H6*D23,2) -> 37.02 | K6: 9 | M6: High | N6: =+'LT cost'!P6/7 -> 92.078571 | O6: =+$N6*C23 -> 53.350429 | P6: =+$N6*D23 -> 38.749598 | Q6: 9.15 | S6: High | T6: =('LT cost'!X6/7) -> 93.514286 | U6: =+$T6*C23 -> 54.182284 | V6: =+$T6*D23 -> 39.353792 | W6: 9.2 | Z6: High | AA6: =('LT cost'!AF6/7) -> 98.732857 | AB6: =+$AA6*C23 -> 57.20593 | AC6: =+$AA6*D23 -> 41.549934 | AD6: 9.5 | AG6: High | AH6: =('LT cost'!AN6/7) -> 105.51571 | AI6: =+$AH6*AB23 -> 61.135925 | AJ6: =+$AH6*AC23 -> 44.404376 | AK6: 10.5 | AN6: High | AO6: =ROUND('LT cost'!AV6/7,2) -> 112.9 | AP6: =+$AO6*AI23 -> 65.41426 | AQ6: =+$AO6*AJ23 -> 47.48574 | AR6: 11.2
A7: Complex | B7: 123.83 | C7: 53.78 | D7: 70.04 | E7: 8 | G7: Complex | H7: =+B7+$I$24 -> 125.97286 | I7: =ROUND(+$H7*C24,2) -> 54.71 | J7: =ROUND(+$H7*D24,2) -> 71.25 | K7: 9 | M7: Complex | N7: =+'LT cost'!P7/7 -> 131.84143 | O7: =+$N7*C24 -> 57.259404 | P7: =+$N7*D24 -> 74.571377 | Q7: 9.15 | S7: Complex | T7: =('LT cost'!X7/7) -> 133.89857 | U7: =+$T7*C24 -> 58.152832 | V7: =+$T7*D24 -> 75.734926 | W7: 9.2 | Z7: Complex | AA7: =('LT cost'!AF7/7) -> 141.37 | AB7: =+$AA7*C24 -> 61.397711 | AC7: =+$AA7*D24 -> 79.960872 | AD7: 9.5 | AG7: Complex | AH7: =('LT cost'!AN7/7) -> 151.08143 | AI7: =+$AH7*AB24 -> 65.615434 | AJ7: =+$AH7*AC24 -> 85.453794 | AK7: 10.5 | AN7: Complex | AO7: =ROUND('LT cost'!AV7/7,2) -> 161.66 | AP7: =+$AO7*AI24 -> 70.208938 | AQ7: =+$AO7*AJ24 -> 91.451062 | AR7: 11.2
A9: Name | G9: Name | M9: Name | S9: Name | Z9: Name | AG9: Name | AN9: Name | AO9: HW
A10: Matrix score | B10: =N10 -> Medium | G10: Matrix score | H10: =N10 -> Medium | M10: Matrix score | N10: Medium | S10: Matrix score | T10: Low | Z10: Matrix score | AA10: Low | AG10: Matrix score | AH10: Complex | AN10: Matrix score | AO10: Complex
B11: number | C11: rate | H11: number | I11: rate | N11: number | O11: rate | T11: number | U11: rate | AA11: number | AB11: rate | AH11: number | AI11: rate | AO11: number | AP11: rate
A12: 24 hr period | B12: =N12 -> 7 | C12: =VLOOKUP($B$10,$A$3:$E$7,2,FALSE) -> 65.04 | D12: =B12*C12 -> 455.28 | G12: 24 hr period | H12: =N12 -> 7 | I12: =VLOOKUP($H$10,$G$3:$K$7,2,FALSE) -> 67.182857 | J12: =H12*I12 -> 470.28 | M12: 24 hr period | N12: 7 | O12: =VLOOKUP($H$10,$M$3:$Q$7,2,FALSE) -> 70.315714 | P12: =N12*O12 -> 492.21 | S12: 24 hr period | T12: 1 | U12: =VLOOKUP($T$10,$S$3:$W$7,2,FALSE) -> 51.302857 | V12: =T12*U12 -> 51.302857 | Z12: 24 hr period | AA12: 1 | AB12: =VLOOKUP($AA$10,$Z$3:$AD$7,2,FALSE) -> 54.165714 | AC12: =AA12*AB12 -> 54.165714 | AG12: 24 hr period | AH12: 1 | AI12: =VLOOKUP($AH$10,$AG$3:$AK$7,2,FALSE) -> 151.08143 | AJ12: =AH12*AI12 -> 151.08143 | AN12: 24 hr period | AO12: 2 | AP12: =_xlfn.XLOOKUP($AO$10,$AN$4:$AN$7,AO4:AO7) -> 161.66 | AQ12: =AO12*AP12 -> 323.32
A13: JUST nights | B13: =N13 -> 0 | C13: =VLOOKUP($B$10,$A$3:$E$7,3,FALSE) -> 40.97 | D13: =B13*C13 -> 0 | G13: JUST nights | H13: =N13 -> 0 | I13: =VLOOKUP($H$10,$G$3:$K$7,3,FALSE) -> 42.32 | J13: =H13*I13 -> 0 | M13: JUST nights | O13: =VLOOKUP($H$10,$M$3:$Q$7,3,FALSE) -> 44.293278 | P13: =N13*O13 -> 0 | S13: JUST nights | T13: 2 | U13: =VLOOKUP($T$10,$S$3:$W$7,3,FALSE) -> 33.04874 | V13: =T13*U13 -> 66.09748 | Z13: JUST nights | AA13: 2 | AB13: =VLOOKUP($AA$10,$Z$3:$AD$7,3,FALSE) -> 34.892961 | AC13: =AA13*AB13 -> 69.785922 | AG13: JUST nights | AH13: 2 | AI13: =VLOOKUP($AH$10,$AG$3:$AK$7,3,FALSE) -> 65.615434 | AJ13: =AH13*AI13 -> 131.23087 | AN13: JUST nights | AO13: 0 | AP13: =_xlfn.XLOOKUP($AO$10,$AN$4:$AN$7,AP4:AP7) -> 70.208938 | AQ13: =AO13*AP13 -> 0
A14: JUST days | B14: =N14 -> 0 | C14: =VLOOKUP($B$10,$A$3:$E$7,4,FALSE) -> 24.08 | D14: =B14*C14 -> 0 | G14: JUST days | H14: =N14 -> 0 | I14: =VLOOKUP($B$10,$G$3:$K$7,4,FALSE) -> 24.87 | J14: =H14*I14 -> 0 | M14: JUST days | O14: =VLOOKUP($B$10,$M$3:$Q$7,4,FALSE) -> 26.033247 | P14: =N14*O14 -> 0 | S14: JUST days | T14: 4 | U14: =VLOOKUP($T$10,$S$3:$W$7,4,FALSE) -> 18.265241 | V14: =T14*U14 -> 73.060964 | Z14: JUST days | AA14: 4 | AB14: =VLOOKUP($AA$10,$Z$3:$AD$7,4,FALSE) -> 19.284498 | AC14: =AA14*AB14 -> 77.13799 | AG14: JUST days | AH14: 4 | AI14: =VLOOKUP($AH$10,$AG$3:$AK$7,4,FALSE) -> 85.453794 | AJ14: =AH14*AI14 -> 341.81517 | AN14: JUST days | AO14: 0 | AP14: =_xlfn.XLOOKUP($AO$10,$AN$4:$AN$7,AQ4:AQ7) -> 91.451062 | AQ14: =AO14*AP14 -> 0
A15: TOTAL INCOME TO CARER | D15: =SUM(D12:D14) -> 455.28 | G15: TOTAL INCOME TO CARER | J15: =SUM(J12:J14) -> 470.28 | M15: TOTAL INCOME TO CARER | P15: =SUM(P12:P14) -> 492.21 | S15: TOTAL INCOME TO CARER | V15: =SUM(V12:V14) -> 190.4613 | Z15: TOTAL INCOME TO CARER | AC15: =SUM(AC12:AC14) -> 201.08963 | AG15: TOTAL INCOME TO CARER | AJ15: =SUM(AJ12:AJ14) -> 624.12747 | AN15: TOTAL INCOME TO CARER | AQ15: =SUM(AQ12:AQ14) -> 323.32
A16: LESS SU contribution | B16: =N16 -> 0 | C16: =VLOOKUP($B$10,$A$3:$E$7,5,FALSE) -> 8 | D16: =B16*C16 -> 0 | G16: LESS SU contribution | H16: =N16 -> 0 | I16: =VLOOKUP($B$10,$G$3:$K$7,5,FALSE) -> 9 | J16: =H16*I16 -> 0 | M16: LESS SU contribution | O16: =VLOOKUP($B$10,$M$3:$Q$7,5,FALSE) -> 9.15 | P16: =N16*O16 -> 0 | S16: LESS SU contribution | U16: =VLOOKUP($T$10,$S$3:$W$7,5,FALSE) -> 9.2 | V16: =T16*U16 -> 0 | Z16: LESS SU contribution | AB16: =VLOOKUP($AA$10,$Z$3:$AD$7,5,FALSE) -> 9.5 | AC16: =AA16*AB16 -> 0 | AG16: LESS SU contribution | AI16: =VLOOKUP($AH$10,$AG$3:$AK$7,5,FALSE) -> 10.5 | AJ16: =AH16*AI16 -> 0 | AN16: LESS SU contribution | AO16: 2 | AP16: =_xlfn.XLOOKUP($AO$10,$AN$4:$AN$7,AR4:AR7) -> 11.2 | AQ16: =AO16*AP16 -> 22.4
A17: TOTAL PAYMENT FROM NCC | D17: =D15-D16 -> 455.28 | G17: TOTAL PAYMENT FROM NCC | J17: =J15-J16 -> 470.28 | M17: TOTAL PAYMENT FROM NCC | P17: =P15-P16 -> 492.21 | S17: TOTAL PAYMENT FROM NCC | V17: =V15-V16 -> 190.4613 | Z17: TOTAL PAYMENT FROM NCC | AC17: =AC15-AC16 -> 201.08963 | AG17: TOTAL PAYMENT FROM NCC | AJ17: =AJ15-AJ16 -> 624.12747 | AN17: TOTAL PAYMENT FROM NCC | AQ17: =AQ15-AQ16 -> 300.92
G19: Total Change since April 2018 | J19: =+J15-D15 -> 15
G20: NCC Change since April 2018 | J20: =+J17-D17 -> 15
C21: =+(C4/$B4) -> 0.64418907 | D21: =+(D4/$B4) -> 0.35602775 | AB21: =+(AB4/$AA4) -> 0.64418907 | AC21: =+(AC4/$AA4) -> 0.35602775 | AI21: =+ROUND((AI4/$AH4),4) -> 0.6442 | AJ21: =1-AI21 -> 0.3558
C22: =+(C5/$B5) -> 0.62992005 | D22: =+(D5/$B5) -> 0.3702337 | AB22: =+(AB5/$AA5) -> 0.62992005 | AC22: =+(AC5/$AA5) -> 0.3702337 | AI22: =+ROUND((AI5/$AH5),4) -> 0.6299 | AJ22: =1-AI22 -> 0.3701
C23: =+(C6/$B6) -> 0.57940114 | D23: =+(D6/$B6) -> 0.42083188 | G23: Weekly Increase | I23: 15 | AB23: =+(AB6/$AA6) -> 0.57940114 | AC23: =+(AC6/$AA6) -> 0.42083188 | AI23: =+ROUND((AI6/$AH6),4) -> 0.5794 | AJ23: =1-AI23 -> 0.4206
C24: =+(C7/$B7) -> 0.4343051 | D24: =+(D7/$B7) -> 0.56561415 | G24: Daily Increase | I24: =+I23/7 -> 2.1428571 | AB24: =+(AB7/$AA7) -> 0.4343051 | AC24: =+(AC7/$AA7) -> 0.56561415 | AI24: =+ROUND((AI7/$AH7),4) -> 0.4343 | AJ24: =1-AI24 -> 0.5657
G30: For Commissioning Purposes | M30: For Commissioning Purposes | S30: For Commissioning Purposes | Z30: For Commissioning Purposes | AG30: For Commissioning Purposes | AN30: For Commissioning Purposes
G32: Arrival Date | I32: 43556 | M32: Arrival Date | O32: 43556 | S32: Arrival Date | U32: 43556 | Z32: Arrival Date | AB32: 43556 | AG32: Arrival Date | AI32: 43556 | AN32: Arrival Date | AP32: 45383
G33: Departure Date | I33: 43559 | M33: Departure Date | O33: 43559 | S33: Departure Date | U33: 43559 | Z33: Departure Date | AB33: 43559 | AG33: Departure Date | AI33: 43559 | AN33: Departure Date | AP33: 45386
G34: No of Nights | I34: =+I33-I32 -> 3 | M34: No of Nights | O34: =+O33-O32 -> 3 | S34: No of Nights | U34: =+U33-U32 -> 3 | Z34: No of Nights | AB34: =+AB33-AB32 -> 3 | AG34: No of Nights | AI34: =+AI33-AI32 -> 3 | AN34: No of Nights | AP34: =+AP33-AP32 -> 3
G36: Effective weekly cost for Mosaic | I36: =+J17/I34*7 -> 1097.32 | M36: Effective weekly cost for Mosaic | O36: =+P17/O34*7 -> 1148.49 | S36: Effective weekly cost for Mosaic | U36: =+V17/U34*7 -> 444.4097 | Z36: Effective weekly cost for Mosaic | AB36: =+AC17/AB34*7 -> 469.20913 | AG36: Effective weekly cost for Mosaic | AI36: =+AJ17/AI34*7 -> 1456.2974 | AN36: Effective weekly cost for Mosaic | AP36: =+AQ17/AP34*7 -> 702.14667
G38: Payment to Carer | I38: =+I36/7*I34 -> 470.28 | M38: Payment to Carer | O38: =+O36/7*O34 -> 492.21 | S38: Payment to Carer | U38: =+U36/7*U34 -> 190.4613 | Z38: Payment to Carer | AB38: =+AB36/7*AB34 -> 201.08963 | AG38: Payment to Carer | AI38: =+AI36/7*AI34 -> 624.12747 | AN38: Payment to Carer | AP38: =+AP36/7*AP34 -> 300.92

Sheet day service or outreach
A1: Day Service or Outreach | F1: Day Service or Outreach | K1: Day Service or Outreach | P1: Day Service or Outreach | U1: Day Service or Outreach | AA1: Day Service or Outreach | AG1: Day Service or Outreach
A2: 2018/19 Rates | F2: 2019/20 Rates | K2: 2020-21 Rates | P2: 2021/22 Rates | U2: 2022/23 Rates | AA2: 2023/24 Rates | AG2: 2024/25 Rates
A3: need level | B3: matrix rate for alternative service per session | F3: need level | G3: matrix rate for alternative service per session | K3: need level | L3: matrix rate for alternative service per session | P3: need level | Q3: matrix rate for alternative service per session | U3: Need level | V3: matrix rate for alternative service per session | AA3: Need level | AB3: matrix rate for alternative service per session | AG3: Need level | AH3: matrix rate per session
A4: Basic | B4: n/a | F4: Basic | G4: n/a | K4: Basic | L4: n/a | P4: Basic | Q4: n/a | U4: Basic | V4: n/a | AA4: Basic | AB4: n/a | AG4: Basic | AH4: n/a
A5: Low | B5: 8.74 | F5: Low | G5: 9.05 | K5: Low | L5: 9.47 | P5: Low | Q5: =ROUND(L5*1.0165,2) -> 9.63 | U5: Low | V5: =ROUND(Q5*1.0558,2) -> 10.17 | AA5: Low | AB5: =ROUND(V5*1.0687,2) -> 10.87 | AG5: Low | AH5: =ROUND(AB5*1.07,2) -> 11.63
A6: Medium | B6: 12.69 | F6: Medium | G6: 13.13 | K6: Medium | L6: 13.74 | P6: Medium | Q6: =ROUND(L6*1.0165,2) -> 13.97 | U6: Medium | V6: =ROUND(Q6*1.0558,2) -> 14.75 | AA6: Medium | AB6: =ROUND(V6*1.0687,2) -> 15.76 | AG6: Medium | AH6: =ROUND(AB6*1.07,2) -> 16.86
A7: High | B7: 17.92 | F7: High | G7: 18.55 | K7: High | L7: 19.41 | P7: High | Q7: =ROUND(L7*1.0165,2) -> 19.73 | U7: High | V7: =ROUND(Q7*1.0558,2) -> 20.83 | AA7: High | AB7: =ROUND(V7*1.0687,2) -> 22.26 | AG7: High | AH7: =ROUND(AB7*1.07,2) -> 23.82
A8: Complex | B8: 34.75 | F8: Complex | G8: 35.96 | K8: Complex | L8: 37.63 | P8: Complex | Q8: =ROUND(L8*1.0165,2) -> 38.25 | U8: Complex | V8: =ROUND(Q8*1.0558,2) -> 40.38 | AA8: Complex | AB8: =ROUND(V8*1.0687,2) -> 43.15 | AG8: Complex | AH8: =ROUND(AB8*1.07,2) -> 46.17
A11: Name | F11: Name | K11: Name | P11: Name | U11: Name | AA11: Name | AG11: Name
A12: Matrix score | B12: =L12 -> Complex | F12: Matrix score | G12: =L12 -> Complex | K12: Matrix score | L12: Complex | P12: Matrix score | Q12: Complex | U12: Matrix score | V12: Complex | AA12: Matrix score | AB12: High | AG12: Matrix score | AH12: Complex
B13: number | C13: rate | G13: number | H13: rate | L13: number | M13: rate | Q13: number | R13: rate | V13: number | W13: rate | AB13: number | AC13: rate | AH13: number | AI13: rate
A14: 1/2 day sessions or outreach contacts per week | B14: =L14 -> 10 | C14: =VLOOKUP(B12,A4:B8,2,FALSE) -> 34.75 | D14: =B14*C14 -> 347.5 | F14: 1/2 day sessions or outreach contacts per week | G14: =L14 -> 10 | H14: =VLOOKUP(G12,F4:G8,2,FALSE) -> 35.96 | I14: =G14*H14 -> 359.6 | K14: 1/2 day sessions or outreach contacts per week | L14: 10 | M14: =VLOOKUP(L12,K4:L8,2,FALSE) -> 37.63 | N14: =L14*M14 -> 376.3 | P14: 1/2 day sessions or outreach contacts per week | Q14: 10 | R14: =VLOOKUP(Q12,P4:Q8,2,FALSE) -> 38.25 | S14: =Q14*R14 -> 382.5 | U14: 1/2 day sessions or outreach contacts per week | V14: 10 | W14: =VLOOKUP(V12,U4:V8,2,FALSE) -> 40.38 | X14: =V14*W14 -> 403.8 | AA14: 1/2 day sessions or outreach contacts per week | AC14: =VLOOKUP(AB12,AA4:AB8,2,FALSE) -> 22.26 | AD14: =AB14*AC14 -> 0 | AG14: 1/2 day sessions or outreach contacts per week | AH14: 2 | AI14: =VLOOKUP(AH12,AG4:AH8,2,FALSE) -> 46.17 | AJ14: =AH14*AI14 -> 92.34
F16: NCC Change since April 2018 | I16: =+I14-$D14 -> 12.1

Sheet ST protected rates
A1: Name
A2: Matrix score | F2: Customer nightly contribution £10.50
B3: number | C3: rate
A4: 24 hr period | C4: =23.76*2 -> 47.52 | D4: =B4*C4 -> 0
A5: 12 hrs over night | C5: 23.76 | D5: =B5*C5 -> 0
A6: 12 hrs just daytime | C6: 23.76 | D6: =B6*C6 -> 0
A7: TOTAL INCOME TO CARER | D7: =SUM(D4:D6) -> 0
A8: LESS SU contribution | B8: =B4+B5 -> 0 | D8: =B8*C8 -> 0
A9: TOTAL PAYMENT FROM NCC | D9: =D7-D8 -> 0
